README.md
setup.cfg
setup.py
gan_encryption_helper/__init__.py
gan_encryption_helper/des_encryption_algorithm.py
gan_encryption_helper/parameter_encoder.py
gan_encryption_helper/parameter_encoder_test.py
gan_encryption_helper.egg-info/PKG-INFO
gan_encryption_helper.egg-info/SOURCES.txt
gan_encryption_helper.egg-info/dependency_links.txt
gan_encryption_helper.egg-info/not-zip-safe
gan_encryption_helper.egg-info/top_level.txt