Metadata-Version: 1.1
Name: gan-encryption-helper
Version: 0.1
Summary: GAN Encryption Helper
Home-page: https://github.com/LordBastor/gan_encryption_helper.git
Author: Bastor
Author-email: lordbastor@gmail.com
License: MIT
Download-URL: https://github.com/LordBastor/gan_encryption_helper/archive/0.1.tar.gz
Platform: UNKNOWN
